{
  "kind": "collectionType",
  "collectionName": "restaurants",
  "info": {
    "singularName": "restaurant",
    "pluralName": "restaurants",
    "displayName": "Restaurant"
  },
  "options": {
    "draftAndPublish": true
  },
  "pluginOptions": {},
  "attributes": {
    "name": {
      "type": "string"
    },
    "address": {
      "type": "string"
    },
    "status": {
      "type": "enumeration",
      "enum": [
        "active",
        "inactive",
        "delete"
      ],
      "default": "active"
    }
  }
}
